microsoft_azure_sphere_deviceapi/__init__.py
microsoft_azure_sphere_deviceapi-0.1.3.dist-info/LICENSE.txt
microsoft_azure_sphere_deviceapi-0.1.3.dist-info/METADATA
microsoft_azure_sphere_deviceapi-0.1.3.dist-info/WHEEL
microsoft_azure_sphere_deviceapi-0.1.3.dist-info/top_level.txt
microsoft_azure_sphere_deviceapi-0.1.3.dist-info/RECORD
