Metadata-Version: 2.1
Name: microsoft-azure-sphere-deviceapi
Version: 0.1.3
Summary: A library for interacting with Azure Sphere devices using the inbuilt REST server.
Author: Microsoft
Author-email: azspheremfrsamplesup@microsoft.com
License: MIT
Classifier: License :: OSI Approved :: MIT License
Classifier: Programming Language :: Python :: 3
Classifier: Operating System :: OS Independent
Requires-Python: >=3.8
License-File: LICENSE.txt
Requires-Dist: azuresphere-device-api
